CHANGES.txt
MANIFEST.in
setup.py
awsjump/__init__.py
awsjump/jump
awsjump.egg-info/PKG-INFO
awsjump.egg-info/SOURCES.txt
awsjump.egg-info/dependency_links.txt
awsjump.egg-info/requires.txt
awsjump.egg-info/top_level.txt