Metadata-Version: 1.1
Name: awsjump
Version: 0.0.4
Summary: Command line tool to SSH into EC2 servers from multiple accounts
Home-page: https://github.com/ministryofjustice/awsjump
Author: Stuart Munro
Author-email: stuart.munro@digital.justice.gov.uk
License: MIT
Platform: Posix; MacOS X
Classifier: Intended Audience :: Developers
Classifier: License :: OSI Approved :: MIT License
Classifier: Topic :: Internet
